pytheos/__init__.py
pytheos/conversion.py
pytheos/eqn_anharmonic.py
pytheos/eqn_bm3.py
pytheos/eqn_debye.py
pytheos/eqn_electronic.py
pytheos/eqn_hugoniot.py
pytheos/eqn_jamieson.py
pytheos/eqn_kunc.py
pytheos/eqn_therm.py
pytheos/eqn_therm_Dorogokupets2007.py
pytheos/eqn_therm_Dorogokupets2015.py
pytheos/eqn_therm_Speziale.py
pytheos/eqn_therm_Tange.py
pytheos/eqn_therm_constq.py
pytheos/eqn_vinet.py
pytheos/etc.py
pytheos/fit_anharmonic.py
pytheos/fit_electronic.py
pytheos/fit_static.py
pytheos/fit_thermal.py
pytheos/plot/__init__.py
pytheos/plot/static_fit.py
pytheos/plot/thermal_fit.py
pytheos/scales/gold.py
pytheos/scales/objs.py
pytheos/scales/periclase.py
pytheos/scales/platinum.py
pytheos-0.0.1.dev30.dist-info/DESCRIPTION.rst
pytheos-0.0.1.dev30.dist-info/METADATA
pytheos-0.0.1.dev30.dist-info/RECORD
pytheos-0.0.1.dev30.dist-info/WHEEL
pytheos-0.0.1.dev30.dist-info/metadata.json
pytheos-0.0.1.dev30.dist-info/pbr.json
pytheos-0.0.1.dev30.dist-info/top_level.txt
