Metadata-Version: 2.0
Name: pytheos
Version: 0.0.1.dev30
Summary: A python tool set for equations of state
Home-page: http://github.com/SHDShim/pytheos
Author: S.-H. Dan Shim
Author-email: shdshim@gmail.com
License: Apache-2
Keywords: setup
Requires-Dist: lmfit
Requires-Dist: matplotlib
Requires-Dist: numpy
Requires-Dist: scipy
Requires-Dist: uncertainties
